arp_jarvis_eventstream-0.3.8.dist-info/licenses/LICENSE
jarvis_event_stream/__init__.py
jarvis_event_stream/__main__.py
jarvis_event_stream/app.py
jarvis_event_stream/config.py
jarvis_event_stream/errors.py
jarvis_event_stream/service.py
jarvis_event_stream/sqlite.py
jarvis_event_stream/utils.py
arp_jarvis_eventstream-0.3.8.dist-info/METADATA
arp_jarvis_eventstream-0.3.8.dist-info/WHEEL
arp_jarvis_eventstream-0.3.8.dist-info/entry_points.txt
arp_jarvis_eventstream-0.3.8.dist-info/top_level.txt
arp_jarvis_eventstream-0.3.8.dist-info/RECORD
