Metadata-Version: 2.4
Name: arp-jarvis-eventstream
Version: 0.3.8
Summary: JARVIS Event Stream internal service for RunEvent storage and NDJSON streaming.
Author: Agent Runtime Protocol
License-Expression: MIT
Requires-Python: >=3.11
License-File: LICENSE
Requires-Dist: fastapi>=0.110.0
Requires-Dist: pydantic>=2.6.0
Requires-Dist: arp-standard-model==0.3.7
Requires-Dist: arp-standard-server==0.3.7
Requires-Dist: uvicorn>=0.29.0
Provides-Extra: dev
Requires-Dist: pyright>=1.1.0; extra == "dev"
Requires-Dist: pytest>=7; extra == "dev"
Requires-Dist: pytest-cov>=4; extra == "dev"
Requires-Dist: httpx>=0.23.0; extra == "dev"
Dynamic: license-file
